django_dbtemplate-0.4.2.dist-info/WHEEL
django_dbtemplate-0.4.2.dist-info/metadata.json
django_dbtemplate-0.4.2.dist-info/DESCRIPTION.rst
django_dbtemplate-0.4.2.dist-info/METADATA
django_dbtemplate-0.4.2.dist-info/RECORD
django_dbtemplate-0.4.2.dist-info/top_level.txt
dbtemplate/models.pyc
dbtemplate/apps.py
dbtemplate/apps.pyc
dbtemplate/tryrenderer.pyc
dbtemplate/__init__.pyc
dbtemplate/models.py
dbtemplate/admin.py
dbtemplate/loader.py
dbtemplate/admin.pyc
dbtemplate/__init__.py
dbtemplate/loader.pyc
dbtemplate/tryrenderer.py
dbtemplate/migrations/0001_initial.py
dbtemplate/migrations/0001_initial.pyc
dbtemplate/migrations/__init__.pyc
dbtemplate/migrations/__init__.py
dbtemplate/templates/admin/dbtemplate/template/change_form.html
dbtemplate/locale/ru_RU/LC_MESSAGES/django.mo
dbtemplate/locale/ru_RU/LC_MESSAGES/django.po
dbtemplate/tests/test_app.py
dbtemplate/tests/test_get_text_context.py
dbtemplate/tests/test_loader.py
dbtemplate/tests/__init__.py
dbtemplate/tests/app/urls.py
dbtemplate/tests/app/models.py
dbtemplate/tests/app/__init__.py
