Metadata-Version: 2.0
Name: django-dbtemplate
Version: 0.4.2
Summary: Allow to override templates from admin interface
Home-page: https://github.com/subuk/django-dbtemplate
Author: Matvey Kruglov
Author-email: kubuzzzz@gmail.com
License: UNKNOWN
Platform: UNKNOWN
Requires-Dist: django
Requires-Dist: pyyaml
Provides-Extra: develop
Requires-Dist: mixer; extra == 'develop'
